xiaomi_ble/__init__.py
xiaomi_ble/cloud.py
xiaomi_ble/const.py
xiaomi_ble/devices.py
xiaomi_ble/events.py
xiaomi_ble/locks.py
xiaomi_ble/parser.py
xiaomi_ble/py.typed
xiaomi_ble-1.6.0.dist-info/METADATA
xiaomi_ble-1.6.0.dist-info/WHEEL
xiaomi_ble-1.6.0.dist-info/licenses/LICENSE
xiaomi_ble-1.6.0.dist-info/RECORD
